{"title":"GreenKart - veg and fruits kart","items":{"cart_info":{"area":[1139,30,73,36],"hasImage":true},"screen":{"area":[0,0,1488,3640],"hasImage":true},"productsimage-24":{"area":[992,2080,200,358],"hasImage":true},"productsimage-25":{"area":[296,2470,200,358],"hasImage":true},"productsimage-26":{"area":[528,2470,200,358],"hasImage":true},"productsimage-27":{"area":[760,2470,200,358],"hasImage":true},"productsimage-28":{"area":[992,2470,200,358],"hasImage":true},"cart_icon":{"area":[1228,30,32,36],"hasImage":true},"productsimage-29":{"area":[296,2860,200,358],"hasImage":true},"productsimage-1":{"area":[296,130,200,358],"hasImage":true},"productsimage-4":{"area":[992,130,200,358],"hasImage":true},"productsimage-20":{"area":[992,1690,200,358],"hasImage":true},"productsimage-5":{"area":[296,520,200,358],"hasImage":true},"productsimage-21":{"area":[296,2080,200,358],"hasImage":true},"productsimage-2":{"area":[528,130,200,358],"hasImage":true},"productsimage-22":{"area":[528,2080,200,358],"hasImage":true},"productsimage-3":{"area":[760,130,200,358],"hasImage":true},"productsimage-23":{"area":[760,2080,200,358],"hasImage":true},"productsimage-8":{"area":[992,520,200,358],"hasImage":true},"productsimage-9":{"area":[296,910,200,358],"hasImage":true},"productsimage-6":{"area":[528,520,200,358],"hasImage":true},"productsimage-7":{"area":[760,520,200,358],"hasImage":true},"Logo":{"area":[364,30,125,35],"hasImage":true},"productsimage-13":{"area":[296,1300,200,358],"hasImage":true},"productsimage-14":{"area":[528,1300,200,358],"hasImage":true},"productsimage-15":{"area":[760,1300,200,358],"hasImage":true},"productsimage-16":{"area":[992,1300,200,358],"hasImage":true},"productsimage-17":{"area":[296,1690,200,358],"hasImage":true},"productsimage-18":{"area":[528,1690,200,358],"hasImage":true},"viewport":{"area":[0,0,1488,3640],"hasImage":true},"productsimage-19":{"area":[760,1690,200,358],"hasImage":true},"search_button":{"area":[831,30,81,36],"hasImage":true},"cart_image":{"area":[1228,30,32,35],"hasImage":true},"productsimage-30":{"area":[528,2860,200,358],"hasImage":true},"productsimage-10":{"area":[528,910,200,358],"hasImage":true},"productsimage-11":{"area":[760,910,200,358],"hasImage":true},"productsimage-12":{"area":[992,910,200,358],"hasImage":true}},"pageName":"Home page"}